{
    "rules": [
      {
        "id": "podfile-changes",
        "name": "Podfile Changes",
        "type": "file_modified",
        "severity": "warning",
        "patterns": ["**/Podfile", "**/Podfile.lock"],
        "message": "Podfile changes detected. Please ensure dependencies are properly reviewed."
      },
      {
        "id": "core-data-changes",
        "name": "Core Data Model Changes",
        "type": "file_modified",
        "severity": "error",
        "patterns": ["**/*.xcdatamodeld/**/*"],
        "message": "Core Data model changes detected. Database migration may be required."
      },
      {
        "id": "deprecated-api-usage",
        "name": "Deprecated API Usage",
        "type": "api_usage",
        "severity": "warning",
        "patterns": ["**/*.swift", "**/*.m", "**/*.h"],
        "forbidden_apis": [
          "UIWebView",
          "dispatch_get_current_queue",
          "UIAlertView",
          "UIActionSheet"
        ],
        "message": "Deprecated API usage detected: {api}. Please use modern alternatives."
      },
      {
        "id": "hardcoded-strings",
        "name": "Hardcoded Strings",
        "type": "api_usage",
        "severity": "warning",
        "patterns": ["**/*.swift"],
        "regex_patterns": [
          "NSLocalizedString\\s*\\(\\s*\"[^\"]+\"\\s*,\\s*comment:\\s*\"\"\\s*\\)"
        ],
        "message": "Empty comment in NSLocalizedString found. Please provide meaningful comments for translators."
      },
      {
        "id": "print-statements",
        "name": "Print Statements",
        "type": "api_usage",
        "severity": "warning",
        "patterns": ["**/*.swift"],
        "regex_patterns": ["\\bprint\\s*\\("],
        "message": "Print statements found. Consider using proper logging instead."
      },
      {
        "id": "force-unwrap",
        "name": "Force Unwrapping",
        "type": "api_usage",
        "severity": "error",
        "patterns": ["**/*.swift"],
        "regex_patterns": ["\\w+!\\s*(?:\\.|\\[|$)"],
        "message": "Force unwrapping detected. Please use safe unwrapping techniques.",
        "exclude_patterns": ["**/*Test*.swift", "**/*Mock*.swift"]
      },
      {
        "id": "info-plist-changes",
        "name": "Info.plist Changes",
        "type": "file_modified",
        "severity": "warning",
        "patterns": ["**/Info.plist"],
        "message": "Info.plist changes detected. Please verify all changes are intentional."
      },
      {
        "id": "network-security",
        "name": "Network Security",
        "type": "api_usage_in_file",
        "severity": "error",
        "file_patterns": ["**/NetworkManager.swift", "**/APIClient.swift"],
        "forbidden_apis": ["http://", "NSURLConnection"],
        "message": "Insecure network usage in {file}. Use HTTPS and modern networking APIs."
      },
      {
        "id": "ui-main-thread",
        "name": "UI Updates on Main Thread",
        "type": "api_usage",
        "severity": "warning",
        "patterns": ["**/*.swift"],
        "regex_patterns": [
          "DispatchQueue\\.global\\(.*\\)\\.async\\s*\\{[^}]*\\b(?:self\\.)?\\w+\\.(text|backgroundColor|isHidden|alpha|frame|bounds|center)"
        ],
        "message": "Potential UI update on background thread detected. Ensure UI updates are on main thread."
      }
    ]
  }